adri_storage/__init__.py
adri_storage/client.py
adri_storage/client_enums.py
adri_storage/client_factory.py
adri_storage/local_client.py
adri_storage/s3_client.py
adri_storage-0.0.5.dist-info/METADATA
adri_storage-0.0.5.dist-info/WHEEL
adri_storage-0.0.5.dist-info/top_level.txt
adri_storage-0.0.5.dist-info/RECORD
