Metadata-Version: 2.1
Name: adri_storage
Version: 0.0.5
Summary: ADRI Storage Python SDK
Author-email: Khalid Rasool <khalid.rasool@adri.nz>, Eslam Allam <eslam.allam@adri.nz>
Classifier: Programming Language :: Python :: 3
Classifier: License :: OSI Approved :: MIT License
Classifier: Operating System :: OS Independent
Requires-Python: >=3.8
Requires-Dist: boto3 ==1.18.0
Requires-Dist: botocore ==1.21.0
Requires-Dist: requests ==2.26.0
